xiplot_filetypes/__init__.py
xiplot_filetypes-1.0.dist-info/METADATA
xiplot_filetypes-1.0.dist-info/WHEEL
xiplot_filetypes-1.0.dist-info/entry_points.txt
xiplot_filetypes-1.0.dist-info/top_level.txt
xiplot_filetypes-1.0.dist-info/RECORD
