Metadata-Version: 2.1
Name: xiplot-filetypes
Version: 1.0
Summary: Xiplot plugin for additional file types
Author-email: Anton Björklund <anton.bjorklund@helsinki.fi>
Project-URL: homepage, https://github.com/edahelsinki/xiplot
Project-URL: repository, https://github.com/edahelsinki/xiplot.git
Classifier: Programming Language :: Python :: 3
Classifier: License :: OSI Approved :: MIT License
Classifier: Operating System :: OS Independent
Requires-Python: >=3.7
Requires-Dist: pandas
Requires-Dist: pyarrow >=11.0.0 ; platform_system != "Emscripten"
Requires-Dist: fastparquet ; platform_system == "Emscripten"
